{
  "name": "Data Stream",
  "width": 40,
  "height": 15,
  "theme": 3,
  "map": [
    "########################################",
    "#                                      #",
    "#       *         *         *          #",
    "#      II        II        II          #",
    "#                                      #",
    "#                                      #",
    "#            H                         #",
    "#          _____             *     E   #",
    "#  P                        II    ###  #",
    "# ###                       II         #",
    "#                                      #",
    "#        B        B       B            #",
    "#      #####    #####   #####          #",
    "#      vvvvv^^^^vvvvv^^^vvvvv          #",
    "########################################"
  ],
  "movingPlatforms": [
    { "x": 22, "y": 8, "width": 2, "height": 0.8, "rangeX": 0, "rangeY": -4, "speed": 100 }
  ],
  "patrols": [
    { "x": 11, "y": 6, "rangeX": 160, "speed": 80 },
    { "x": 26, "y": 11, "rangeX": 80, "speed": 90 }
  ]
}
